embedders/__init__.py
embedders/enums.py
embedders/util.py
embedders/classification/__init__.py
embedders/classification/contextual.py
embedders/classification/count_based.py
embedders/classification/reduce.py
embedders/extraction/__init__.py
embedders/extraction/contextual.py
embedders/extraction/count_based.py
embedders/extraction/reduce.py
embedders/samples/__init__.py
embedders/samples/clickbait.py
embedders-0.1.8.dist-info/LICENSE
embedders-0.1.8.dist-info/METADATA
embedders-0.1.8.dist-info/WHEEL
embedders-0.1.8.dist-info/top_level.txt
embedders-0.1.8.dist-info/RECORD
