Metadata-Version: 2.1
Name: embedders
Version: 0.1.8
Summary: High-level API for creating sentence and token embeddings
Home-page: https://github.com/code-kern-ai/embedders
Author: Johannes Hötter
Author-email: johannes.hoetter@kern.ai
License: UNKNOWN
Keywords: kern,machine learning,representation learning,python
Platform: UNKNOWN
Classifier: Development Status :: 3 - Alpha
Classifier: Programming Language :: Python :: 3
Classifier: License :: OSI Approved :: MIT License
License-File: LICENSE
Requires-Dist: numpy
Requires-Dist: scikit-learn
Requires-Dist: sentence-transformers
Requires-Dist: spacy (>=3.0.0)
Requires-Dist: torch (>=1.6.0)
Requires-Dist: tqdm
Requires-Dist: transformers (<5.0.0,>=4.6.0)
Requires-Dist: openai
Requires-Dist: cohere
